LICENSE
MANIFEST.in
README.md
compy.py
setup.cfg
setup.py
ascompy.egg-info/PKG-INFO
ascompy.egg-info/SOURCES.txt
ascompy.egg-info/dependency_links.txt
ascompy.egg-info/top_level.txt
src/__init__.py